AUTHORS
LICENSE
MANIFEST.in
setup.py
django_mongoforms.egg-info/PKG-INFO
django_mongoforms.egg-info/SOURCES.txt
django_mongoforms.egg-info/dependency_links.txt
django_mongoforms.egg-info/not-zip-safe
django_mongoforms.egg-info/top_level.txt
mongoforms/__init__.py
mongoforms/fields.py
mongoforms/forms.py
mongoforms/utils.py
testprj/__init__.py
testprj/manage.py
testprj/settings.py
testprj/tests.py
testprj/urls.py
testprj/testapp/__init__.py
testprj/testapp/decorators.py
testprj/testapp/documents.py
testprj/testapp/forms.py
testprj/testapp/models.py
testprj/testapp/tests.py
testprj/testapp/urls.py
testprj/testapp/views.py