Metadata-Version: 1.0
Name: django-mongoforms
Version: 0.2
Summary: A Django-ModelForm clone for mongoengine
Home-page: http://github.com/stephrdev/django-mongoforms/
Author: Serge Matveenko
Author-email: s@matveenko.ru
License: UNKNOWN
Platform: UNKNOWN
Classifier: Development Status :: 3 - Alpha
Classifier: Environment :: Web Environment
Classifier: Intended Audience :: Developers
Classifier: License :: OSI Approved :: BSD License
Classifier: Operating System :: OS Independent
Classifier: Programming Language :: Python
Classifier: Framework :: Django
